{"ongoing_trials": {}, "hyperparameters": {"space": [{"class_name": "Int", "config": {"name": "num_layers", "default": null, "conditions": [], "min_value": 1, "max_value": 11, "step": 1, "sampling": null}}, {"class_name": "Int", "config": {"name": "units_0", "default": null, "conditions": [], "min_value": 8, "max_value": 256, "step": 8, "sampling": null}}, {"class_name": "Choice", "config": {"name": "activation", "default": "relu", "conditions": [], "values": ["relu", "tanh", "sigmoid"], "ordered": false}}, {"class_name": "Boolean", "config": {"name": "dropout", "default": false, "conditions": []}}, {"class_name": "Float", "config": {"name": "lr", "default": 0.0001, "conditions": [], "min_value": 0.0001, "max_value": 0.1, "step": null, "sampling": "log"}}, {"class_name": "Int", "config": {"name": "units_1", "default": null, "conditions": [], "min_value": 8, "max_value": 256, "step": 8, "sampling": null}}, {"class_name": "Int", "config": {"name": "units_2", "default": null, "conditions": [], "min_value": 8, "max_value": 256, "step": 8, "sampling": null}}, {"class_name": "Int", "config": {"name": "units_3", "default": null, "conditions": [], "min_value": 8, "max_value": 256, "step": 8, "sampling": null}}, {"class_name": "Int", "config": {"name": "units_4", "default": null, "conditions": [], "min_value": 8, "max_value": 256, "step": 8, "sampling": null}}, {"class_name": "Int", "config": {"name": "units_5", "default": null, "conditions": [], "min_value": 8, "max_value": 256, "step": 8, "sampling": null}}, {"class_name": "Int", "config": {"name": "units_6", "default": null, "conditions": [], "min_value": 8, "max_value": 256, "step": 8, "sampling": null}}, {"class_name": "Int", "config": {"name": "units_7", "default": null, "conditions": [], "min_value": 8, "max_value": 256, "step": 8, "sampling": null}}, {"class_name": "Int", "config": {"name": "units_8", "default": null, "conditions": [], "min_value": 8, "max_value": 256, "step": 8, "sampling": null}}, {"class_name": "Int", "config": {"name": "units_9", "default": null, "conditions": [], "min_value": 8, "max_value": 256, "step": 8, "sampling": null}}, {"class_name": "Choice", "config": {"name": "dr", "default": 0.25, "conditions": [], "values": [0.25, 0.5], "ordered": true}}, {"class_name": "Int", "config": {"name": "units_10", "default": null, "conditions": [], "min_value": 8, "max_value": 256, "step": 8, "sampling": null}}], "values": {"num_layers": 1, "units_0": 8, "activation": "relu", "dropout": false, "lr": 0.0001, "units_1": 8, "units_2": 8, "units_3": 8, "units_4": 8, "units_5": 8, "units_6": 8, "units_7": 8, "units_8": 8, "units_9": 8, "dr": 0.25, "units_10": 8}}, "seed": 2047, "seed_state": 2063, "tried_so_far": ["afe8821e8574c492910092e6e68b74f4", "cc1eaa8d623cc02519759c24f89fbce5"], "num_initial_points": 2, "alpha": 0.0001, "beta": 2.6}